pyrbit/__init__.py
pyrbit/abc.py
pyrbit/actr.py
pyrbit/design.py
pyrbit/ef.py
pyrbit/information.py
pyrbit/mem_utils.py
pyrbit/mle_utils.py
pyrbit/plot_utils.py
pyrbit-0.1.1.dist-info/LICENSE
pyrbit-0.1.1.dist-info/WHEEL
pyrbit-0.1.1.dist-info/METADATA
pyrbit-0.1.1.dist-info/RECORD
