Metadata-Version: 2.1
Name: pyrbit
Version: 0.1.1
Summary: Utilities for parametric modeling of Recall based interaction techniques
License: MIT
Author: jgori
Author-email: juliengori@gmail.com
Requires-Python: >=3.8,<3.12
Classifier: License :: OSI Approved :: MIT License
Classifier: Programming Language :: Python :: 3
Classifier: Programming Language :: Python :: 3.10
Classifier: Programming Language :: Python :: 3.8
Classifier: Programming Language :: Python :: 3.9
Requires-Dist: Sphinx (<=7.0)
Requires-Dist: arviz (>=0.15.1,<0.16.0)
Requires-Dist: matplotlib (>=3.7.1,<4.0.0)
Requires-Dist: numpy (>=1.24.2,<2.0.0)
Requires-Dist: pymc (>=5.6.0,<6.0.0)
Requires-Dist: scipy (>=1.10.1,<2.0.0)
Requires-Dist: seaborn (>=0.12.2,<0.13.0)
Requires-Dist: sphinx-rtd-theme (>=1.3.0,<2.0.0)
Requires-Dist: statsmodels (>=0.14.0,<0.15.0)
Requires-Dist: sympy (>=1.12,<2.0)
Requires-Dist: tqdm (>=4.65.0,<5.0.0)
